digitalfemsa/__init__.py
digitalfemsa/api_client.py
digitalfemsa/api_response.py
digitalfemsa/configuration.py
digitalfemsa/exceptions.py
digitalfemsa/py.typed
digitalfemsa/rest.py
digitalfemsa/api/__init__.py
digitalfemsa/api/api_keys_api.py
digitalfemsa/api/balances_api.py
digitalfemsa/api/charges_api.py
digitalfemsa/api/companies_api.py
digitalfemsa/api/customers_api.py
digitalfemsa/api/discounts_api.py
digitalfemsa/api/events_api.py
digitalfemsa/api/logs_api.py
digitalfemsa/api/orders_api.py
digitalfemsa/api/payment_link_api.py
digitalfemsa/api/payment_methods_api.py
digitalfemsa/api/products_api.py
digitalfemsa/api/shipping_contacts_api.py
digitalfemsa/api/shippings_api.py
digitalfemsa/api/taxes_api.py
digitalfemsa/api/transactions_api.py
digitalfemsa/api/transfers_api.py
digitalfemsa/api/webhook_keys_api.py
digitalfemsa/api/webhooks_api.py
digitalfemsa/models/__init__.py
digitalfemsa/models/api_key_create_response.py
digitalfemsa/models/api_key_request.py
digitalfemsa/models/api_key_response.py
digitalfemsa/models/api_key_response_on_delete.py
digitalfemsa/models/api_key_update_request.py
digitalfemsa/models/balance_common_field.py
digitalfemsa/models/balance_response.py
digitalfemsa/models/charge_order_response.py
digitalfemsa/models/charge_order_response_payment_method.py
digitalfemsa/models/charge_request.py
digitalfemsa/models/charge_request_payment_method.py
digitalfemsa/models/charge_response.py
digitalfemsa/models/charge_response_channel.py
digitalfemsa/models/charge_response_payment_method.py
digitalfemsa/models/charge_response_refunds.py
digitalfemsa/models/charge_response_refunds_data.py
digitalfemsa/models/charge_update_request.py
digitalfemsa/models/charges_data_response.py
digitalfemsa/models/checkout.py
digitalfemsa/models/checkout_order_template.py
digitalfemsa/models/checkout_order_template_customer_info.py
digitalfemsa/models/checkout_request.py
digitalfemsa/models/checkout_response.py
digitalfemsa/models/checkouts_response.py
digitalfemsa-1.0.0.dist-info/LICENSE
digitalfemsa-1.0.0.dist-info/METADATA
digitalfemsa-1.0.0.dist-info/WHEEL
digitalfemsa-1.0.0.dist-info/top_level.txt
digitalfemsa-1.0.0.dist-info/RECORD
